RattleBack/RattleBack.py
RattleBack/__init__.py
RattleBack-0.0.2.dist-info/LICENSE
RattleBack-0.0.2.dist-info/METADATA
RattleBack-0.0.2.dist-info/WHEEL
RattleBack-0.0.2.dist-info/top_level.txt
RattleBack-0.0.2.dist-info/RECORD
