Metadata-Version: 2.1
Name: RattleBack
Version: 0.0.2
Summary: motion of rattle-back
Home-page: https://github.com/tt-nakamura/rattle
Author: Takahiro Nakamura
Author-email: a41757@gmail.com
License: UNKNOWN
Project-URL: Bug Tracker, https://github.com/tt-nakamura/rattle/issues
Platform: UNKNOWN
Classifier: Programming Language :: Python :: 3
Classifier: License :: OSI Approved :: MIT License
Classifier: Operating System :: OS Independent
Requires-Python: >=3.6
License-File: LICENSE
